tabeltests/__init__.py
tabeltests/utils.py
table_test-0.4.1.dist-info/METADATA
table_test-0.4.1.dist-info/WHEEL
table_test-0.4.1.dist-info/top_level.txt
table_test-0.4.1.dist-info/RECORD
