Metadata-Version: 2.1
Name: table-test
Version: 0.4.1
Summary: Simple engine for your test. No code, no noodles
Home-page: https://github.com/Hedgehogues/table-tests
Author: Egor Urvanov
Author-email: hedgehogues@bk.ru
License: UNKNOWN
Platform: UNKNOWN
Classifier: Programming Language :: Python :: 3.7
Classifier: License :: OSI Approved :: MIT License
Classifier: Operating System :: OS Independent
Requires-Dist: deepdiff (==4.0.6)
Requires-Dist: numpy (==1.16.4)
